odoo/addons/l10n_us_account_profile/README.rst
odoo/addons/l10n_us_account_profile/__init__.py
odoo/addons/l10n_us_account_profile/__manifest__.py
odoo/addons/l10n_us_account_profile/i18n/l10n_us_account_profile.pot
odoo/addons/l10n_us_account_profile/readme/CONTRIBUTORS.rst
odoo/addons/l10n_us_account_profile/readme/DESCRIPTION.rst
odoo/addons/l10n_us_account_profile/static/description/icon.png
odoo/addons/l10n_us_account_profile/static/description/index.html
odoo11_addon_l10n_us_account_profile-11.0.1.0.0.99.dev4.dist-info/METADATA
odoo11_addon_l10n_us_account_profile-11.0.1.0.0.99.dev4.dist-info/WHEEL
odoo11_addon_l10n_us_account_profile-11.0.1.0.0.99.dev4.dist-info/top_level.txt
odoo11_addon_l10n_us_account_profile-11.0.1.0.0.99.dev4.dist-info/RECORD
