Metadata-Version: 2.1
Name: odoo11-addon-l10n-us-account-profile
Version: 11.0.1.0.0.99.dev4
Summary: Additional features to manage US accounting in Odoo
Home-page: https://github.com/OCA/l10n-usa
Author: Open Source Integrators, Odoo Community Association (OCA)
Author-email: support@odoo-community.org
License: AGPL-3
Platform: UNKNOWN
Classifier: Programming Language :: Python
Classifier: Framework :: Odoo
Classifier: Framework :: Odoo :: 11.0
Classifier: License :: OSI Approved :: GNU Affero General Public License v3
Requires-Python: >=2.7, !=3.0.*, !=3.1.*, !=3.2.*, !=3.3.*, !=3.4.*
Requires-Dist: odoo11-addon-account-banking-reconciliation
Requires-Dist: odoo11-addon-account-due-list
Requires-Dist: odoo11-addon-account-payment-batch-process
Requires-Dist: odoo11-addon-account-payment-credit-card
Requires-Dist: odoo11-addon-account-reversal
Requires-Dist: odoo11-addon-l10n-us-check-writing-address
Requires-Dist: odoo11-addon-l10n-us-form-1099
Requires-Dist: odoo11-addon-partner-aging
Requires-Dist: odoo11-addon-partner-time-to-pay
Requires-Dist: odoo <11.1dev,>=11.0a
